smarthex/__init__.py
smarthex/cli.py
smarthex/main.py
smarthex-0.2.2.dist-info/licenses/LICENSE
smarthex-0.2.2.dist-info/METADATA
smarthex-0.2.2.dist-info/WHEEL
smarthex-0.2.2.dist-info/entry_points.txt
smarthex-0.2.2.dist-info/top_level.txt
smarthex-0.2.2.dist-info/RECORD
