Metadata-Version: 2.4
Name: smarthex
Version: 0.2.2
Summary: A library for generating and validating SmartHex16 identifiers
Author-email: Victor Matos <contact@byteram.co>
License: MIT
Project-URL: Homepage, https://byteram.co/opensource/smarthex16
Project-URL: Documentation, https://byteram.co/opensource/smarthex16
Project-URL: Repository, https://github.com/Byteram/SmartHex16
Project-URL: Bug Tracker, https://github.com/Byteram/SmartHex16/issues
Classifier: Programming Language :: Python :: 3
Classifier: Programming Language :: Python :: 3.7
Classifier: Programming Language :: Python :: 3.8
Classifier: Programming Language :: Python :: 3.9
Classifier: Programming Language :: Python :: 3.10
Classifier: Programming Language :: Python :: 3.11
Classifier: Operating System :: OS Independent
Classifier: Development Status :: 4 - Beta
Classifier: Intended Audience :: Developers
Classifier: Topic :: Software Development :: Libraries :: Python Modules
Requires-Python: >=3.7
License-File: LICENSE
Provides-Extra: test
Requires-Dist: pytest>=7.0.0; extra == "test"
Requires-Dist: pytest-cov>=4.0.0; extra == "test"
Provides-Extra: dev
Requires-Dist: black>=23.0.0; extra == "dev"
Requires-Dist: isort>=5.0.0; extra == "dev"
Requires-Dist: mypy>=1.0.0; extra == "dev"
Dynamic: license-file
